<?xml version="1.0" ?>
<routes xmlns:xsi="http://www.w3.org/2001/XMLSchema-instance" xsi:noNamespaceSchemaLocation="http://sumo.dlr.de/xsd/routes_file.xsd">


    <!-- Vehicle type definition -->


    <vType id="veh_passenger" vClass="passenger"/>


    <!-- Define circular routes for each vehicle -->


    <route edges="28746384 51568860 28746537#0 51568862 -977668123 -207799106 -507094807 -51568864#1 -51568864#0 -51568854#6 -51568854#5 -51568854#4 -51568854#3 -51568854#2 -51568854#1 -51568854#0 39760590#0 39760590#1 339250826#0 339250826#1 339250826#2 978118038 39760573#0 39760573#1 39760573#2 959155208 945279309 207714800 68338600#0 68338600#1 70562437 -42675703#1 -42675703#0 -42675704#5 -42675704#4 148895698#0 148895698#1 148895698#2 148895698#3 457397324#3 -148895693#4 -148895693#3 -148895693#2 148895694#0 -148895700 -148895697#0" id="route0" repeat="10"/>


    <route edges="4081664 51607737#0 51607737#1 51607737#2 51607737#3 103401623#0 103401623#1 103401623#2 143742719#0 143742719#1 143742719#2 143742719#3 93121887 1051854288 4578541 93121875#0 93121875#1 93121875#2 93121875#3 93121875#4 93121875#5 93121875#6 93121875#7 39760590#0 39760590#1 339250826#0 339250826#1 339250826#2 978118038 39760573#0 39760573#1 39760573#2 959155208 945279309 207714800 68338600#0 68338600#1 70562437 -42675703#1 -42675703#0 -42675704#5 -42675704#4 148895698#0 148895698#1 148895698#2 148895698#3 457397324#3 -148895693#4 -148895693#3 -148895693#2 148895694#0 -148895700 -148895697#0" id="route1" repeat="10"/>


    <route edges="65053911#0 65053911#1 65053911#2 39760563 63951486#0 63951486#1 981008714 2988718#0 2988718#1 2988718#2 2988718#3 2988718#4 2988718#5 2988718#6 65288472#0 65288472#1 65288472#2 65288472#3 65288472#4 65288472#5 65288472#6 65288472#7 65288472#8 399060558#0 399060558#1 4729142#0 148935666#0 148935666#1 148935666#2 1101186959 1101186960 2988675#5 2988675#6 2988675#0 2988675#1 148935673 39760591 148935664 148935662#0 2988624 99858782 977031656#0 977031656#1 977031656#2 33778748 977031653#0 977031653#1 33778749 977031657 977031652 2988628#0 35792141 143749335#0 143749335#1 143749335#2 143749336 856164070#0 856164070#1 856164070#2 -210856077#1 -210856077#0 -457397324#4 -148895693#4 -148895693#3 -148895693#2 148895694#0 -148895700 -148895697#0" id="route2" repeat="10"/>


    <route edges="1186706381#1 148933074#0 148933074#1 148933074#2 -103401623#1 -103401623#0 -51607737#3 -51607737#2 -51607737#1 -51607737#0 51607735#0 51607735#1 4081527#2 4081527#3 4081527#4 4081527#5 4081527#6 4578539 -144033356#1 -144033356#0 -28784368#1 -28784368#0 -28783164 -4081528#6 -4081528#5 -4081528#4 -4081528#3 -4081528#2 1120143632#0" id="route3" repeat="10"/>


    <route edges="39760590#0 39760590#1 339250826#0 339250826#1 339250826#2 978118038 39760573#0 39760573#1 39760573#2 959155208 945279309 207714800 68338600#0 68338600#1 70562437 -42675703#1 -42675703#0 -35792959#1 -35792959#0 -856164070#2 -856164070#1 -856164070#0 35792405 297097142 977031652 33778751 980633550#0 2988625 99858785 148935659#1" id="route4" repeat="10"/>


    <route edges="28783164 28784368#0 28784368#1 144033356#0 144033356#1 4578540 4081527#8 4081527#0 4081664 51607737#0 51607737#1 51607737#2 51607737#3 103401623#0 103401623#1 103401623#2 28746456#0 28746456#1 28746456#2 28746456#3 207799117#0 207799117#1 207799109#3 207799109#4 207799118 207799105" id="route5" repeat="10"/>


    <route edges="-39999437#1 -39999437#0 -977031651#3 -977031651#2 -977031651#1 -977031651#0 -708952496 39999438 980633550#0 2988625 99858785 148935659#1 148935672 39760580 39760588 2988675#3 148935652#0 148935652#1 148935652#2 148935652#3 148935652#4 4729142#2 4729142#3 1089244066 4081528#0 4081528#1 4081528#2 4081528#3 4081528#4 4081528#5 4081528#6 28783164 28784368#0 -28784368#0 28677717 28677727" id="route6" repeat="10"/>


    <route edges="4578544 1051315787#0 1051315787#1 1051315787#2 93121891 -143742719#3 -143742719#2 -143742719#1 -143742719#0 -103401623#2 -103401623#1 -103401623#0 -103401622#7 -103401622#6 -103401622#5 -103401622#4 -103401622#3 -103401622#2 -103401622#1" id="route7" repeat="10"/>


    <route edges="4578543 4081670#0 4081670#1 4081670#2 4081670#3 4081670#4 4081670#5 4081670#6 4081670#7 4081670#8 978248319 791411579 39760565" id="route8" repeat="10"/>


    <route edges="-71617442#1 -71617442#0 4079741#2 4079741#3 1044324165#0 1044324165#1 1044324165#2 71617439 977031650#0 977031650#1 71617435#0 71617435#1 71617435#2 71617435#3 71617435#4 -977031651#3 -977031651#2 -977031651#1 -977031651#0 -708952496 39999438 980633550#0 2988625 99858785 148935659#1 148935672 39760580 39760588 2988675#3 148935652#0 148935652#1 148935652#2 148935652#3 148935652#4 4729142#2 4729142#3 1089244066 4081528#0 4081528#1 4081528#2 4081528#3 4081528#4 4081528#5 4081528#6 28783164 28784368#0 -28784368#0 28677717 28677727 148886950#3 148886950#4 148886950#5 -28677738" id="route9" repeat="10"/>


    <route edges="922740527 922740528 1328396405 1328396406 1328396407 1328396408 42675704#0 42675704#1 42675704#2 42675704#3 42675704#4 42675704#5 -35792959#1 -35792959#0 -856164070#2 -856164070#1 -856164070#0 35792405 297097142 977031652 33778751 980633550#0 980633550#1 33778752 1169725324 977031656#0 977031656#1 -736319115" id="route10" repeat="10"/>


    <route edges="4578543 4578544 1051315787#0 1051315787#1 1051315787#2 1051854287 1051854288 4578541 93121875#0 93121875#1 93121875#2 93121875#3 93121875#4 93121875#5 93121875#6 93121875#7 51568854#0 51568854#1 51568854#2 51568854#3 51568854#4 51568854#5 51568854#6 51568864#0 51568864#1 507094807 117690159 117690162 103401621 -4600230#3 -4600230#2 -4600230#1 -4600230#0 -1114962547 -1213065192#2 -1213065192#1 -1213065192#0 -1068231852 -977031655#1 -977031655#0 -4079720#3 -4079720#2 -4079720#1 -4079720#0 4079723#0" id="route11" repeat="10"/>


    <route edges="148935673 39760591 148935664 148935662#0 2988624 99858782 977031656#0 977031656#1 977031656#2 33778748 977031653#0 977031653#1 33778749 977031657 977031652 33778751 980633550#0 2988625 99858785 148935659#1 148935672 39760580 39760588 2988675#3 148935652#0 148935652#1 148935652#2 148935652#3 148935652#4 4729142#2 4729142#3 1089244066 4081528#0 4081528#1 4081528#2 4081528#3 4081528#4 4081528#5 4081528#6 28783164 28784368#0 28784368#1 144033356#0 144033356#1 4578540 4081527#8 4081527#0 4081527#1 4081527#2 4081527#3 -93179903#1 93179902" id="route12" repeat="10"/>



    <route edges="515712519 977031653#0 977031653#1 33778749 977031657 977031652 33778751 980633550#0 2988625 99858785 148935659#1 148935672 39760580 39760588 2988675#3 148935652#0 148935652#1 148935652#2 148935652#3 148935652#4 4729142#2 4729140#0 4729140#1 4729140#2 51219846 210873500" id="route14" repeat="10"/>


    <route edges="399060558#0 399060558#1 4729142#0 4729142#1 4729142#2 4729140#0 4729140#1 4729140#2 28745980 103401622#0 103401622#1 103401622#2 -126548346#1" id="route15" repeat="10"/>


    <route edges="-4079718 -64489933#2 -64489933#1 -64489933#0 -515712517 4079712 65053911#0 65053911#1 65053911#2 39760563 63951486#0 63951486#1 981008714 2988718#0 2988718#1 2988718#2 2988718#3 2988718#4 2988718#5 2988718#6 65288472#0 65288472#1 65288472#2 65288472#3 65288472#4 65288472#5 65288472#6 65288472#7 65288472#8 399060558#0 399060558#1 4729142#0 4729142#1 4729142#2 4729140#0 4729140#1 4729140#2 51219846 210873500 210873490 51568868#0 51568868#1 954238846 -977668123 -207799106 207799106 977668123 -51568862" id="route16" repeat="10"/>


    <route edges="148895693#2 148895693#3 148895693#4 457397324#4 210856077#0 210856077#1 -856164070#2 -856164070#1 -856164070#0 35792405 297097142 977031652 33778751 980633550#0 2988625 99858785 148935659#1 148935672 39760580 39760588 2988675#3 148935652#0 148935652#1 148935652#2 148935652#3 148935652#4 4729142#2 4729142#3 1089244066 4081528#0 4081528#1 4081528#2" id="route17" repeat="10"/>


    <route edges="-148933074#2 -148933074#1 -148933074#0 -1186706381#1 148933081#0 148933081#1 148933081#2 148933081#3 148933081#4 148933081#5 148933081#6 1359092027 -103401622#7 -103401622#6 -103401622#5 -103401622#4 -103401622#3 -103401622#2 -103401622#1 -103401622#0 28746112 28746121 -210873500 -51219846" id="route18" repeat="10"/>


    <route edges="-977031651#2 -977031651#1 -977031651#0 -708952496 39999438 980633550#0 2988625 99858785 148935659#1 148935672 39760580 39760588 2988675#3 148935652#0 148935652#1 148935652#2 148935652#3 148935652#4 4729142#2 4729142#3 1089244066 4081528#0 4081528#1 4081528#2 4081528#3 4081528#4 4081528#5 4081528#6 28783164 28784368#0 28784368#1 144033356#0 144033356#1 4578540 4081527#8 4081527#0 4081527#1 4081527#2 4081527#3 4081527#4 4578535 148886950#0 -37118068" id="route19" repeat="10"/>


    <route edges="457397324#4 210856077#0 210856077#1 -856164070#2 -856164070#1 -856164070#0 35792405 297097142 977031652 2988628#0 2988628#1 708952496 977031651#0 977031651#1 977031651#2 977031651#3 -71617435#4 -71617435#3 -71617435#2 -71617435#1 -71617435#0 -977031650#1 -977031650#0 -71617439 -1044324165#2 -1044324165#1 -1044324165#0 -4079741#3 -4079741#2 71617442#0 71617442#1" id="route20" repeat="10"/>


    <route edges="-28746357#0 -103401623#1 -103401623#0 -103401622#7 -103401622#6 -103401622#5 -103401622#4 -103401622#3 -103401622#2 -103401622#1 -103401622#0 28746112 28746121 210873490 51568868#0 51568868#1 117690170 981268034 977668122 117690162 103401621 -4600230#3 -4600230#2 -4600230#1 -4600230#0 -1114962547 -1213065192#2 -1213065192#1 -1213065192#0 -1068231852 -977031655#1 -977031655#0 -4079720#3 -4079720#2 -4079720#1 -4079720#0 4079723#0" id="route21" repeat="10"/>


    <route edges="207745041#0 207745041#1 207714800 68338600#0 68338600#1 70562437 -42675703#1 -42675703#0 -35792959#1 -35792959#0 -856164070#2 -856164070#1 -856164070#0 35792405 297097142 977031652 2988628#0 35792141 143749335#0 143749335#1 143749335#2 35792636#0" id="route22" repeat="10"/>


    <route edges="51568859#0 51568859#1 148935653#2 148935653#3 -148935667#3 -148935667#2 -148935667#1 -148935667#0 -1002657611 143483316#0 143483316#1 148935652#2 148935652#3 148935652#4 4729142#2 4729140#0 4729140#1 4729140#2 51219846 210873500 210873490 51568868#0 51568868#1 954238846 -977668123 -207799106 -507094807 -51568864#1 -51568864#0 -51568854#6 -51568854#5 -51568854#4 -51568854#3 -51568854#2 -51568854#1 -51568854#0 39760590#0 39760590#1 339250826#0 339250826#1 339250826#2 978118038 39760573#0 39760573#1 39760573#2 959155208 945279309 207714800 68338600#0 68338600#1 70562437 -42675703#1 -42675703#0 -42675704#5 -42675704#4 148895698#0 148895698#1 148895698#2 148895698#3 -457397324#2" id="route23" repeat="10"/>


    <route edges="-4081528#1 -4081528#0 -1089244066 4729142#4 4729142#5 4729142#0 4729142#1 4729142#2 4729140#0 4729140#1 4729140#2 51219846 210873500 210873490 51568868#0 51568868#1 954238846 -977668123 -207799106 117690159" id="route24" repeat="10"/>


    <route edges="1005641221 1089243172#0 1089243172#1 68338601#0 68338601#1 68338601#2 208585619#0 208585619#1 922740525 1328396408 42675704#0 42675704#1 42675704#2 42675704#3 42675704#4 42675704#5 -35792959#1 -35792959#0 -210856077#1 -210856077#0 -457397324#4" id="route25" repeat="10"/>


    <route edges="35792959#0 35792959#1 42675703#0 42675703#1 68338595#0 68338595#1 71103093#0 71103093#1 71103093#2 71103093#3 71103093#4 71103093#5 71103093#6 71103093#7 71103093#8 71103093#9 1328396412 1328396413 1328396410 4578545 -292124785#2 -292124785#1 -292124785#0 -39760578#3 -39760578#2 -39760578#1 -39760578#0 -39760565 -791411579 -978248319 -4081670#8 -4081670#7 -4081670#6 -4081670#5 -4081670#4 -4081670#3 -4081670#2 -4081670#1 -4081670#0 4578544 1051315787#0 1051315787#1 1051315787#2 1051854287 1051854288 4578541 93121875#0 93121875#1 41479382 862745081#0" id="route26" repeat="10"/>


    <route edges="2988628#1 39999438 980633550#0 2988625 99858785 148935659#1 148935672 39760580 39760588 2988675#3 148935652#0 148935652#1 148935652#2 148935652#3 148935652#4 4729142#2 4729142#3 1089244066" id="route27" repeat="10"/>


    <route edges="70085612#1 70085612#2 70085612#3 70085612#4 70085612#5 70085612#6 70085612#7 51568842#3 -148935667#3 -148935667#2 -148935667#1 -148935667#0 -1002657611 143483316#0 143483316#1 148935652#2 148935652#3 148935652#4 4729142#2 4729142#3 1089244066 4081528#0 4081528#1 4081528#2 4081528#3 4081528#4 4081528#5 4081528#6 28783164 28784368#0 -28784368#0 28677717 28677727 148886950#3 148886950#4 148886950#5 148886950#6 148886950#7" id="route28" repeat="10"/>


    <route edges="207799110 -28746456#3 -41478992 93121875#6 93121875#7 39760590#0 39760590#1 339250826#0 339250826#1 339250826#2 978118038 39760573#0 39760573#1 39760573#2 959155208 945279309 207714800 68338600#0 68338600#1 70562437 -42675703#1 -42675703#0 -42675704#5 -42675704#4 148895698#0 148895698#1 148895698#2 148895698#3 -457397324#2 -457397324#1" id="route29" repeat="10"/>


    <route edges="103689113 339250822 1328396403 1328396404 1328396405 1328396406 922740526 -208585619#1 -208585619#0 -119966264 4812573 1328396410 1328396411 4082162#0 4082162#1 4082162#2 339250823#0 339250823#1 339250823#2 339250823#3 339250823#4 339250823#5 954077216#0 954077216#1 954077216#2 959161079#0 959161079#1 940150024#0 940150024#1 940150024#2 940150024#3 207745041#0 207745041#1 -945279309 -959155208 -39760573#2 -39760573#1 -39760573#0 -978118038 -339250826#2 -339250826#1 -339250826#0 -39760590#1" id="route30" repeat="10"/>


    <route edges="981268034 977668122 -117690159 207799106 977668123 -954238846 -51568868#1 -51568868#0 -210873490 -210873500 -51219846 -4729140#2 -4729140#1 -4729140#0 4729142#3 4729142#4 4729142#5 4729142#0 148935666#0 148935666#1 148935666#2 1101186959 1101186960 2988675#5 2988675#6 2988675#0 2988675#1 148935673 39760591 148935664 148935662#0 148935662#1" id="route31" repeat="10"/>


    <route edges="-148895696#2 -148895696#1 -148895696#0 457397324#1 457397324#2 457397324#3 457397324#4 210856077#0 210856077#1 -856164070#2 -856164070#1 -856164070#0 35792405 297097142 977031652 33778751 980633550#0 2988625 99858785 148935659#1 148935672 39760580 39760588 2988675#3 148935652#0 148935652#1 148935652#2 148935652#3 148935652#4 4729142#2 4729140#0 4729140#1 4729140#2 28745980 103401622#0 103401622#1 103401622#2 -126548346#1" id="route32" repeat="10"/>


    <route edges="-148935669#1 -148935669#0 -210873489#1 -210873489#0 -1169725322#1 -1169725322#0 -1169725323 -4079723#3 -4079723#2 -4079723#1 -4079723#0 4079720#0 4079720#1 4079720#2 4079720#3 977031655#0 977031655#1 1068231852 1213065192#0 1213065192#1 1213065192#2 1114962547 4600230#0 4600230#1 4600230#2 4600230#3 -103401621 -117690162 -117690159 207799106 977668123 -51568862 -28746537#0 891750168 36203420" id="route33" repeat="10"/>


    <route edges="4578539 4578540 4081527#8 4081527#0 4081664 51607737#0 51607737#1 51607737#2 51607737#3 103401623#0 103401623#1 103401623#2 143742719#0 143742719#1 143742719#2 143742719#3 93121887 1051854288 1051854284 1051854283 4578543 4081670#0 4081670#1 4081670#2 4081670#3 4081670#4 4081670#5 4081670#6 4081670#7 4081670#8 978248319 791411579 39760565 39760578#0 39760578#1 39760578#2 39760578#3 292124785#0 292124785#1 292124785#2 4578546 1328396414 207799114 1328396412 119966262#0" id="route34" repeat="10"/>


    <route edges="-148886950#2 -148886950#1 -148886950#0 4578536 4081527#6 4578539 -144033356#1 -144033356#0 -28784368#1 44785978 -44785980#2 -44785980#1 -28745889#3 -28745889#2 -28745889#1 -28745889#0 103401622#0" id="route35" repeat="10"/>


    <route edges="93121887 1051854288 4578541 93121875#0 93121875#1 93121875#2 93121875#3 93121875#4 93121875#5 93121875#6 93121875#7 39760590#0 39760590#1 339250826#0 339250826#1 339250826#2 978118038 39760573#0 39760573#1 39760573#2 959155208 945279309 207714800 68338600#0 68338600#1 70562437 -42675703#1 -42675703#0 -35792959#1 -35792959#0 -856164070#2 -856164070#1 -856164070#0 35792405 297097142 977031652 33778751 980633550#0 980633550#1 33778752 1169725324 977031656#0 977031656#1 977031656#2 515712518 515712519" id="route36" repeat="10"/>


    <route edges="-103401623#1 -103401623#0 -103401622#7 -103401622#6 -103401622#5 -103401622#4 -103401622#3 -103401622#2 -103401622#1 -103401622#0 28746112 28746121 210873490 51568868#0 51568868#1 117690170 981268034 977668122 117690162 103401621 -4600230#3 -4600230#2 -4600230#1 -4600230#0 -1114962547 -1213065192#2 -1213065192#1 -1213065192#0 -1068231852 -977031655#1 -977031655#0 -4079720#3 -4079720#2 -4079720#1 -4079720#0 -4082170#1 -4082170#0 -1039060565#1 -1039060565#0 -65757654#2 -65757654#1 -65757654#0 -64489933#9 -64489933#8 -64489933#7 -64489933#6 -64489933#5 -64489933#4 -64489933#3 -64489933#2 -64489933#1 -64489933#0 -515712517 4079712" id="route37" repeat="10"/>


    <route edges="36203420 -28746357#1 -126548347 -103401622#3 -103401622#2 -103401622#1 -103401622#0 -28745980 -4729140#2 -4729140#1 -4729140#0 4729142#3 4729142#4 4729142#5 4729142#0 148935666#0 148935666#1 148935666#2 1101186959 1101186960 2988675#5 149251355" id="route38" repeat="10"/>


    <route edges="457397324#3 457397324#4 210856077#0 210856077#1 -856164070#2 -856164070#1 -856164070#0 35792405 297097142 977031652 33778751 980633550#0 2988625 99858785 148935659#1 148935672 39760580 39760588 2988675#3 148935652#0 148935652#1 148935652#2 148935652#3 148935652#4 4729142#2 4729140#0 4729140#1 4729140#2 51219846 210873500 210873490 51568868#0 51568868#1 954238846 -977668123 -207799106 -507094807 -51568864#1 -51568864#0 51568864#0 51568864#1 28746384 51568860 28746537#0" id="route39" repeat="10"/>


    <route edges="-207799105 207799116 207799109#6 207799109#0 207799109#1 207799110 -28746456#3 -41478992 93121875#6 93121875#7 51568854#0 51568854#1 51568854#2 51568854#3 51568854#4 51568854#5 51568854#6 51568864#0 51568864#1 507094807 117690159 117690162 103401621 36994790 51568842#0 51568842#1 51568842#2 51568842#3 -148935667#3 -148935667#2 -148935667#1 -148935667#0 -1002657611 143483316#0" id="route40" repeat="10"/>


    <route edges="144033356#0 144033356#1 4578540 4081527#8 4081527#0 4081664 51607737#0 51607737#1 51607737#2 51607737#3 103401623#0 103401623#1 103401623#2 143742719#0 143742719#1 143742719#2 143742719#3 93121887 1051854288 1051854284 1051854283 4578543 4081670#0 4081670#1 4081670#2 4081670#3 4081670#4 4081670#5 4081670#6 4081670#7 4081670#8 978248319 791411579 39760565 39760578#0 39760578#1 39760578#2 39760578#3 292124785#0 292124785#1 292124785#2 4578546 1328396414 207799114 1328396412 119966262#0 119966262#1 119966264 208585619#0 208585619#1 922740525" id="route41" repeat="10"/>


    <route edges="981008714 2988718#0 2988718#1 2988718#2 2988718#3 2988718#4 2988718#5 2988718#6 65288472#0 65288472#1 65288472#2 65288472#3 65288472#4 65288472#5 65288472#6 65288472#7 65288472#8 399060558#0 399060558#1 4729142#0 148935666#0 148935666#1 148935666#2 1101186959 1101186960 2988675#5 2988675#6 2988675#0 2988675#1 148935673 39760591 148935664 148935662#0 2988624 99858782 977031656#0 977031656#1 977031656#2 33778748 977031653#0 977031653#1 33778749 977031657 977031652 2988628#0 35792141 143749335#0 143749335#1 143749335#2 143749336 856164070#0 856164070#1 856164070#2 -210856077#1 -210856077#0 -457397324#4 -457397324#3 -457397324#2" id="route42" repeat="10"/>


    <route edges="148935652#1 148935652#2 148935652#3 148935652#4 4729142#2 4729140#0 4729140#1 4729140#2 51219846 210873500 210873490 51568868#0 51568868#1 954238846 -977668123 -207799106 207799106 977668123 -51568862 -28746537#0 891750168 36203420 -28746357#1" id="route43" repeat="10"/>


    <route edges="70085612#0 70085612#1 70085612#2 70085612#3 70085612#4 70085612#5 70085612#6 70085612#7 51568842#3 -148935667#3 -148935667#2 -148935667#1 -148935667#0 -1002657611 143483316#0 143483316#1 148935652#2 148935652#3 148935652#4 4729142#2 4729142#3 1089244066 4081528#0 4081528#1 4081528#2 4081528#3 4081528#4 4081528#5 4081528#6 28783164 28784368#0 28784368#1 144033356#0 144033356#1 4578540 4081527#8 4081527#0 4081664 51607735#0 51607735#1" id="route44" repeat="10"/>


    <route edges="457397324#2 457397324#3 457397324#4 210856077#0 210856077#1 -856164070#2 -856164070#1 -856164070#0 35792405 297097142 977031652 33778751 980633550#0 2988625 99858785 148935659#1 148935672 39760580 39760588 2988675#3 2988675#4 2988675#5 149251355 -1101183635 -44785601 -44785600 44785600 44785601 1101183635 149251351" id="route45" repeat="10"/>


    <route edges="-1062308945#1 -1062308945#0 -210873489#3 -210873489#2 148935669#0 148935669#1 71617435#0 71617435#1 71617435#2 71617435#3 71617435#4 -977031651#3 -977031651#2 -977031651#1 -977031651#0 -708952496 39999438 980633550#0 980633550#1 33778752 1169725324 977031656#0 977031656#1 977031656#2 33778748 977031653#0 977031653#1 33778749 977031657 977031652 2988628#0 35792141 143749335#0 143749335#1 143749335#2 143749336 856164070#0 856164070#1 856164070#2 35792959#0 35792959#1 42675703#0 42675703#1 68338595#0 68338595#1 71103093#0 71103093#1 71103093#2" id="route46" repeat="10"/>


    <route edges="62317000#0 62317000#1 1186704881#0 1186704881#1 -148886950#6 -148886950#5 -148886950#4 -148886950#3 -148886950#2 -148886950#1 -148886950#0 4578536 4081527#6 4578539 -144033356#1 -144033356#0 -28784368#1 44785978 -44785980#2 -44785980#1 -28745889#3 -28745889#2 -28745889#1 -28745889#0 28746112 28746121 210873490 51568868#0 51568868#1 117690170 981268034 977668122 117690162 103401621 36994790 51568842#0" id="route47" repeat="10"/>


    <route edges="-64489933#2 -64489933#1 -64489933#0 -515712517 4079712 65053911#0 65053911#1 65053911#2 39760563 63951486#0 63951486#1 981008714 2988718#0 2988718#1 2988718#2 2988718#3 2988718#4 2988718#5 2988718#6 65288472#0 65288472#1 65288472#2 65288472#3 65288472#4 65288472#5 65288472#6 65288472#7 65288472#8 399060558#0 399060558#1 4729142#0 4729142#1 4729142#2 4729140#0 4729140#1 4729140#2 51219846 210873500 210873490 51568868#0 51568868#1 954238846 -977668123 -207799106 -507094807 -51568864#1 -51568864#0 -51568854#6 -51568854#5 -51568854#4 -51568854#3 -51568854#2 -51568854#1 -51568854#0 -93121875#7 -93121875#6 -93121875#5 -93121875#4 -93121875#3 -93121875#2 -93121875#1 -93121875#0 4578542 1051854283 4081663 1051315787#0 1051315787#1 1051315787#2 93121891 -143742719#3" id="route48" repeat="10"/>


    <route edges="62317000#0 62317000#1 1186704881#0 1186704881#1 -148886950#6 -148886950#5 -148886950#4 -148886950#3 -148886950#2 -148886950#1 -148886950#0 4578536 4081527#6 4578539 -144033356#1 -144033356#0 -28784368#1 44785978 -44785980#2 -44785980#1 -28745889#3 -28745889#2 -28745889#1 -28745889#0 28746112 28746121 210873490 51568868#0 51568868#1 954238846 -977668123 -207799106 207799106 977668123 -51568862 -28746537#0 891750168" id="route49" repeat="10"/>


    <route edges="-148886950#6 -148886950#5 -148886950#4 -148886950#3 -148886950#2 -148886950#1 -148886950#0 4578536 4081527#6 4081527#7 4081527#8 4081527#0 4081664 51607737#0 51607737#1 51607737#2 51607737#3 103401623#0 103401623#1 103401623#2 143742719#0 143742719#1 143742719#2 143742719#3 93121887 1051854288 4578541 93121875#0 93121875#1 93121875#2 93121875#3 93121875#4 93121875#5 93121875#6 93121875#7 39760590#0 39760590#1 339250826#0 339250826#1 339250826#2 978118038 39760573#0 39760573#1 39760573#2 959155208 945279309 207714800 68338600#0 68338600#1 70562437 -42675703#1" id="route50" repeat="10"/>


    <route edges="44785600 44785601 1101183635 149251351 2988675#1 148935673 39760591 148935664 148935662#0 2988624 99858782 977031656#0 977031656#1 977031656#2 515712518 -208489220#4 -208489220#3" id="route51" repeat="10"/>


    <route edges="148895693#2 148895693#3 148895693#4 -457397324#3 -148895698#3 -148895698#2 -148895698#1 -148895698#0 42675704#4 42675704#5 42675703#0 42675703#1 68338595#0 68338595#1 71103093#0 71103093#1 71103093#2 71103093#3 71103093#4 71103093#5 71103093#6 71103093#7 71103093#8 71103093#9 1328396412 1328396413 1328396410 4578545 -292124785#2 -292124785#1 -292124785#0 -39760578#3 -39760578#2 -39760578#1 -39760578#0 -39760565 -791411579 -978248319 -4081670#8 -4081670#7 -4081670#6 -4081670#5 -4081670#4 -4081670#3 -4081670#2 -4081670#1 -4081670#0 4578544 1051315787#0 1051315787#1 1051315787#2 1051854287 1051854288 4578541 93121875#0 93121875#1 93121875#2 93121875#3 93121875#4 93121875#5 93121875#6 93121875#7 51568854#0 51568854#1 51568854#2 51568854#3 28746474#0 28746474#1 28746474#2 28746474#3 207799109#1 207799110" id="route52" repeat="10"/>


    <route edges="457397324#3 457397324#4 210856077#0 210856077#1 -856164070#2 -856164070#1 -856164070#0 35792405 297097142 977031652 33778751 980633550#0 2988625 99858785 148935659#1 148935672 39760580 39760588 2988675#3 148935652#0 148935652#1 148935652#2 148935652#3 148935652#4 4729142#2 4729142#3 1089244066 4081528#0 4081528#1 4081528#2 4081528#3 4081528#4 4081528#5 4081528#6 28783164 28784368#0 28784368#1 144033356#0 144033356#1 4578540 4081527#8 4081527#0 4081664 51607737#0" id="route53" repeat="10"/>


    <route edges="119966262#0 119966262#1 4812573 1328396410 4578545 -292124785#2 -292124785#1 -292124785#0 -39760578#3 -39760578#2 -39760578#1 -39760578#0 -39760565 -791411579 -978248319 -4081670#8 -4081670#7 -4081670#6 -4081670#5 -4081670#4 -4081670#3 -4081670#2 -4081670#1 -4081670#0 4578544 1051315787#0 1051315787#1 1051315787#2 1051854287 1051854288 4578541 93121875#0 93121875#1 93121875#2 93121875#3 93121875#4 93121875#5 93121875#6 93121875#7 51568854#0 51568854#1 51568854#2 51568854#3 51568854#4 51568854#5 51568854#6 51568864#0 51568864#1 507094807 207799106 977668123 -954238846 -51568868#1 -51568868#0 -210873490 -210873500 -51219846 -4729140#2 -4729140#1 -4729140#0 4729142#3 4729142#4 399060559 -65288472#8 -65288472#7 -65288472#6 -65288472#5 -65288472#4 -65288472#3 -65288472#2 -65288472#1 -65288472#0 -2988718#6 -2988718#5 -2988718#4 -2988718#3 -2988718#2 -2988718#1 -2988718#0 -981008714 -981008713 -37141755" id="route54" repeat="10"/>


    <route edges="148935673 39760591 148935664 148935662#0 2988624 99858782 977031656#0 977031656#1 977031656#2 33778748 977031653#0 977031653#1 33778749 977031657 977031652 2988628#0 2988628#1 708952496 977031651#0 977031651#1 977031651#2 977031651#3 -71617435#4 -71617435#3 -71617435#2 -71617435#1 -71617435#0 -148935669#1 -148935669#0 -210873489#1" id="route55" repeat="10"/>


    <route edges="-31578831#4 -31578831#3 -37882841 208489220#2 208489220#3 208489220#4 515712519 977031653#0 977031653#1 33778749 977031657 977031652 2988628#0 35792141 143749335#0 143749335#1 143749335#2 143749336 856164070#0 856164070#1 856164070#2 35792959#0 35792959#1 42675703#0 42675703#1 68338595#0 68338595#1 71103093#0 71103093#1 1005641221" id="route56" repeat="10"/>


    <route edges="981008714 2988718#0 2988718#1 2988718#2 2988718#3 2988718#4 2988718#5 2988718#6 65288472#0 65288472#1 65288472#2 65288472#3 65288472#4 65288472#5 65288472#6 65288472#7 65288472#8 399060558#0 399060558#1 4729142#0 148935666#0 148935666#1 148935666#2 1101186959 1101186960 2988675#5 2988675#6 2988675#0 2988675#1 148935673 39760591 148935664 148935662#0 2988624 99858782 977031656#0 977031656#1 977031656#2 33778748 977031653#0 977031653#1 33778749 977031657 977031652 2988628#0 2988628#1" id="route57" repeat="10"/>


    <route edges="208585619#0 208585619#1 922740525 1328396408 42675704#0 42675704#1 42675704#2 42675704#3 42675704#4 42675704#5 -35792959#1 -35792959#0 -856164070#2 -856164070#1 -856164070#0 35792405 297097142 977031652 2988628#0 2988628#1 708952496 977031651#0 977031651#1 977031651#2 977031651#3 39999437#0 39999437#1 39999437#2" id="route58" repeat="10"/>


    <route edges="-71617442#0 4079741#2 4079741#3 1044324165#0 1044324165#1 1044324165#2 71617439 977031650#0 977031650#1 71617435#0 71617435#1 71617435#2 71617435#3 71617435#4 -977031651#3 -977031651#2 -977031651#1 -977031651#0 -708952496 39999438 980633550#0 2988625 99858785 148935659#1 148935672 39760580 39760588 2988675#3 148935652#0 148935652#1 148935652#2 148935652#3 148935652#4 4729142#2 4729142#3 1089244066 4081528#0 4081528#1 4081528#2 4081528#3 4081528#4 4081528#5 4081528#6 28783164 28784368#0 -28784368#0 28677717" id="route59" repeat="10"/>


    <route edges="-4081528#1 -4081528#0 -1089244066 4729142#4 4729142#5 4729142#0 4729142#1 4729142#2 4729140#0 4729140#1 4729140#2 51219846 210873500 210873490 51568868#0 51568868#1 954238846 -977668123 -207799106 -507094807 -51568864#1 -51568864#0 -51568854#6 -51568854#5 -51568854#4 -51568854#3 -51568854#2 -51568854#1 -51568854#0 39760590#0" id="route60" repeat="10"/>


    <route edges="-148886950#8 -148886950#7 -148886950#6 -148886950#5 -148886950#4 -148886950#3 -148886950#2 -148886950#1 -148886950#0 4578536 4081527#6 4578539 -144033356#1 -144033356#0 -28784368#1 44785978 -44785980#2 -44785980#1 -28745889#3 -28745889#2 -28745889#1 -28745889#0 28746112 28746121 210873490 51568868#0 51568868#1 954238846 -977668123 -207799106 -507094807 -51568864#1 -51568864#0 51568864#0 51568864#1 28746384" id="route61" repeat="10"/>


    <route edges="-4081528#1 -4081528#0 -1089244066 4729142#4 4729142#5 4729142#0 4729142#1 4729142#2 4729140#0 4729140#1 4729140#2 51219846 210873500 210873490 51568868#0 51568868#1 954238846 -977668123 -207799106 -507094807 -51568864#1 -51568864#0 -51568854#6 -51568854#5 -51568854#4 -51568854#3 -51568854#2 -51568854#1 -51568854#0 39760590#0 39760590#1 339250826#0 339250826#1 339250826#2 978118038 39760573#0 39760573#1 39760573#2 959155208 945279309 207714800 68338600#0" id="route62" repeat="10"/>


    <route edges="515712519 977031653#0 977031653#1 33778749 977031657 977031652 33778751 980633550#0 2988625 99858785 148935659#1 148935672 39760580 39760588 2988675#3 148935652#0 148935652#1 148935652#2 148935652#3 148935652#4 4729142#2 4729142#3 1089244066 4081528#0 4081528#1 4081528#2 4081528#3 4081528#4 4081528#5 4081528#6 28783164 28784368#0 -28784368#0 28677717 28677727 148886950#3" id="route63" repeat="10"/>




    <route edges="736319116 736319115 977031656#2 33778748 977031653#0 977031653#1 33778749 977031657 977031652 33778751 980633550#0 2988625 99858785 148935659#1 148935672 39760580 39760588 2988675#3 148935652#0 148935652#1 148935652#2 148935652#3 148935652#4 4729142#2 4729140#0 4729140#1 4729140#2 51219846 210873500 210873490" id="route65" repeat="10"/>


    <route edges="148895693#0 -148895689 148895693#3 148895693#4 457397324#4 210856077#0 210856077#1 -856164070#2 -856164070#1 -856164070#0 35792405 297097142 977031652 33778751 980633550#0 2988625 99858785 148935659#1 148935672 39760580 39760588 2988675#3 148935652#0 148935652#1 148935652#2 148935652#3 148935652#4 4729142#2 4729142#3 1089244066 4081528#0 4081528#1 4081528#2 4081528#3 4081528#4 4081528#5 4081528#6 28783164 28784368#0 28784368#1 144033356#0 144033356#1 4578540 4081527#8 4081527#0 4081527#1 4081527#2 4081527#3 4081527#4 4578535 4578536" id="route66" repeat="10"/>


    <route edges="4578543 4081670#0 4081670#1 4081670#2 4081670#3 4081670#4 4081670#5 4081670#6 4081670#7 4081670#8 978248319 791411579 39760565 39760578#0" id="route67" repeat="10"/>


    <route edges="-148895698#3 -148895698#2 -148895698#1 -148895698#0 42675704#4 42675704#5 42675703#0 42675703#1 68338595#0 68338595#1 71103093#0 71103093#1 71103093#2 71103093#3 71103093#4 71103093#5 71103093#6 71103093#7 71103093#8 71103093#9 1328396412 1328396413 1328396410 4578545 -292124785#2 -292124785#1 -292124785#0 -39760578#3 -39760578#2 -39760578#1 -39760578#0 -39760565 -791411579 -978248319 -4081670#8 -4081670#7 -4081670#6 -4081670#5 -4081670#4 -4081670#3 -4081670#2 -4081670#1 -4081670#0 4578544 1051315787#0 1051315787#1 1051315787#2 93121891 -143742719#3 -143742719#2 -143742719#1 -143742719#0 -103401623#2 -103401623#1 -103401623#0 -103401622#7 -103401622#6 -103401622#5 -103401622#4 126548347" id="route68" repeat="10"/>


    <route edges="119966262#0 119966262#1 119966264 208585619#0 208585619#1 922740525 1328396408 42675704#0 42675704#1 42675704#2 42675704#3 148895698#0 148895698#1 148895698#2 148895698#3 457397324#3 -148895693#4 -148895693#3 148895689 -148895693#0" id="route69" repeat="10"/>


    <route edges="4081526#0 4081526#1 -1120143632#3 -1120143632#2 -1120143632#1 -1120143632#0 4081528#2 4081528#3 4081528#4 4081528#5 4081528#6 28783164 28784368#0 28784368#1 144033356#0 144033356#1 4578540 4081527#8 4081527#0 4081664 51607737#0 51607737#1 51607737#2 51607737#3 103401623#0 103401623#1 103401623#2 143742719#0 143742719#1 143742719#2 143742719#3 93121887 1051854288 1051854284 1051854283 4578543 4081670#0 4081670#1 4081670#2 4081670#3 4081670#4 4081670#5 4081670#6 4081670#7 4081670#8 978248319 791411579 39760565 39760578#0 39760578#1 39760578#2 39760578#3 292124785#0 292124785#1 292124785#2 4578546 1328396414 207799114 1328396412 119966262#0 119966262#1 119966264 208585619#0 208585619#1 922740525 1328396408 1328396409 103689113 339250821#0" id="route70" repeat="10"/>


    <route edges="977668122 -117690159 -507094807 -51568864#1 -51568864#0 -51568854#6 -51568854#5 -51568854#4 -51568854#3 -51568854#2 -51568854#1 -51568854#0 39760590#0 39760590#1 339250826#0 339250826#1 339250826#2 978118038 39760573#0 39760573#1 39760573#2 959155208 945279309 207714800 68338600#0 68338600#1 70562437 -42675703#1 -42675703#0 -42675704#5 -42675704#4 148895698#0 148895698#1 148895698#2 148895698#3 457397324#3 -148895693#4 -148895693#3 -148895693#2 148895694#0 -148895700 -148895697#0" id="route71" repeat="10"/>


    <route edges="1039060565#0 1039060565#1 4082170#0 4082170#1 4079720#0 4079720#1 4079720#2 4079720#3 977031655#0 977031655#1 1068231852 1213065192#0 1213065192#1 1213065192#2 1114962547 4600230#0 4600230#1 4600230#2 4600230#3 -103401621 -117690162 -117690159 -507094807 -51568864#1 -51568864#0 -51568854#6 -51568854#5 -51568854#4 -51568854#3 -51568854#2 -51568854#1 -51568854#0 -93121875#7 -93121875#6 -93121875#5 -93121875#4 -93121875#3 -93121875#2 -93121875#1 -93121875#0 4578542 1051854283 4578543 4081670#0" id="route72" repeat="10"/>


    <route edges="515712519 977031653#0 977031653#1 33778749 977031657 977031652 2988628#0 35792141 143749335#0 143749335#1 143749335#2 143749336 856164070#0 856164070#1 856164070#2 35792959#0 35792959#1 -42675704#5 -42675704#4 -42675704#3" id="route73" repeat="10"/>


    <route edges="2988718#0 2988718#1 2988718#2 2988718#3 2988718#4 2988718#5 2988718#6 65288472#0 65288472#1 65288472#2 65288472#3 65288472#4 65288472#5 65288472#6 65288472#7 65288472#8 399060558#0 399060558#1 4729142#0 148935666#0 148935666#1 148935666#2 1101186959 1101186960 2988675#5 2988675#6 2988675#0 2988675#1 148935673 39760591 148935664 148935662#0 2988624 99858782 977031656#0 977031656#1 977031656#2 33778748 977031653#0 977031653#1 33778749 977031657 977031652 2988628#0 35792141 143749335#0 143749335#1 143749335#2 143749336 856164070#0 856164070#1 856164070#2 -210856077#1 -210856077#0 -457397324#4 -457397324#3 -457397324#2 -143742721#1" id="route74" repeat="10"/>


    <route edges="1186706381#1 148933074#0 148933074#1 148933074#2 -103401623#1 -103401623#0 -103401622#7 -103401622#6 -103401622#5 -103401622#4 -103401622#3 -103401622#2 -103401622#1 -103401622#0 28746112 28746121 -210873500 -51219846" id="route75" repeat="10"/>


    <route edges="-42675704#3 -42675704#2 -42675704#1 -42675704#0 1328396409 25383761 1328396403 1328396404 1328396405 1328396406 922740526 -208585619#1 -208585619#0 -119966264 4812573 1328396410 4578545 -292124785#2 -292124785#1 -292124785#0 -39760578#3 -39760578#2 -39760578#1 -39760578#0 -39760565 -791411579 -978248319 -4081670#8 -4081670#7 -4081670#6 -4081670#5 -4081670#4 -4081670#3 -4081670#2 -4081670#1 -4081670#0 4578544 1051315787#0 1051315787#1 1051315787#2 1051854287 1051854288 4578541 93121875#0 93121875#1 93121875#2 93121875#3 93121875#4 93121875#5 93121875#6 93121875#7 51568854#0 51568854#1 51568854#2 51568854#3 51568854#4 51568854#5 51568854#6 51568864#0 51568864#1 507094807 117690159 117690162 103401621 36994790 51568842#0 51568842#1 51568842#2 -70085612#7 -70085612#6 -70085612#5 -70085612#4 -70085612#3 -70085612#2 -70085612#1 70085613" id="route76" repeat="10"/>


    <route edges="143742719#1 143742719#2 143742719#3 93121887 1051854288 4578541 93121875#0 93121875#1 93121875#2 93121875#3 93121875#4 93121875#5 93121875#6 93121875#7 39760590#0 39760590#1 339250826#0 339250826#1 339250826#2 978118038 39760573#0 39760573#1 39760573#2 959155208 945279309 207714800 68338600#0 68338600#1 70562437 -42675703#1 -42675703#0 -35792959#1 -35792959#0 -856164070#2 -856164070#1 -856164070#0 35792405 297097142 977031652 33778751 980633550#0 980633550#1 33778752 1169725324 977031656#0 977031656#1 977031656#2 515712518 515712519" id="route77" repeat="10"/>


    <route edges="149251355 -1101183635 -44785601 -44785600 44785600 44785601 1101183635 149251351 2988675#1 2988675#2 2988675#3 148935652#0 148935652#1 148935652#2 148935652#3 148935652#4 4729142#2 4729140#0 4729140#1 4729140#2 28745980 103401622#0 103401622#1 103401622#2 103401622#3 103401622#4 103401622#5 103401622#6 103401622#7 -1359092027" id="route78" repeat="10"/>




    <route edges="93121887 1051854288 4578541 93121875#0 93121875#1 93121875#2 93121875#3 93121875#4 93121875#5 93121875#6 93121875#7 39760590#0 39760590#1 339250826#0 339250826#1 339250826#2 978118038 39760573#0 39760573#1 39760573#2 959155208 945279309 207714800 68338600#0 68338600#1 68338598 71103093#0" id="route80" repeat="10"/>


    <route edges="-148895696#0 457397324#1 457397324#2 457397324#3 457397324#4 210856077#0 210856077#1 -856164070#2 -856164070#1 -856164070#0 35792405 297097142 977031652 33778751 980633550#0 980633550#1 33778752 1169725324 977031656#0 977031656#1 977031656#2 515712518 -208489220#4 -208489220#3 -208489220#2 37882841" id="route81" repeat="10"/>


    <route edges="1039060565#0 1039060565#1 4082170#0 4082170#1 4079723#0 4079723#1 4079723#2 4079723#3 1169725323 1169725322#0 1169725322#1 210873489#0 210873489#1 148935669#0 148935669#1 71617435#0 71617435#1 71617435#2 71617435#3 71617435#4 -977031651#3 -977031651#2 -977031651#1 -977031651#0 -708952496 39999438 980633550#0 980633550#1 33778752 1169725324 977031656#0 977031656#1 977031656#2 33778748 977031653#0 977031653#1 33778749 977031657 977031652 2988628#0 35792141 143749335#0 143749335#1 143749335#2 143749336 856164070#0 856164070#1 856164070#2 -210856077#1 -210856077#0 -457397324#4 -457397324#3 -457397324#2 -143742721#1 -143742721#0" id="route82" repeat="10"/>




    <route edges="-457397324#3 -148895698#3 -148895698#2 -148895698#1 -148895698#0 42675704#4 42675704#5 42675703#0 42675703#1 68338595#0 68338595#1 71103093#0 71103093#1 71103093#2 71103093#3 71103093#4 71103093#5 71103093#6 71103093#7 71103093#8 71103093#9 1328396412 1328396413 1328396410 4578545 -292124785#2 -292124785#1 -292124785#0 -39760578#3 -39760578#2 -39760578#1 -39760578#0 -39760565 -791411579 -978248319 -4081670#8 -4081670#7 -4081670#6 -4081670#5 -4081670#4 -4081670#3 -4081670#2 -4081670#1 -4081670#0 4578544 1051315787#0 1051315787#1 1051315787#2 93121891 -143742719#3 -143742719#2 -143742719#1 -143742719#0 -103401623#2 -103401623#1 -103401623#0 -51607737#3 -51607737#2 -51607737#1 -51607737#0 51607735#0 51607735#1 4081527#2 4081527#3 4081527#4 4578535" id="route84" repeat="10"/>


    <route edges="-148886950#2 -148886950#1 -148886950#0 4578536 4081527#6 4081527#7 4081527#8 4081527#0 4081664 51607737#0 51607737#1 51607737#2 51607737#3 103401623#0 103401623#1 103401623#2 143742719#0 143742719#1 143742719#2 143742719#3 93121887 1051854288 1051854284 1051854283 4578543 4081670#0 4081670#1 4081670#2 4081670#3 4081670#4 4081670#5 4081670#6 4081670#7 4081670#8 978248319 791411579 39760565 39760578#0 39760578#1 39760578#2 39760578#3 292124785#0 292124785#1 292124785#2 4578546 1328396414 207799114 1328396412 119966262#0 119966262#1 119966264" id="route85" repeat="10"/>


    <route edges="922740527 922740528 1328396405 1328396406 922740526 -208585619#1 -208585619#0 -119966264 4812573 1328396410 4578545 -292124785#2 -292124785#1 -292124785#0 -39760578#3 -39760578#2 -39760578#1 -39760578#0 -39760565 -791411579 -978248319 -4081670#8 -4081670#7 -4081670#6 -4081670#5 -4081670#4 -4081670#3 -4081670#2 -4081670#1 -4081670#0 4578544 1051315787#0 1051315787#1 1051315787#2 1051854287 1051854288 4578541 93121875#0 93121875#1 93121875#2 93121875#3 93121875#4 93121875#5 93121875#6 93121875#7 51568854#0 51568854#1 51568854#2 51568854#3 51568854#4 51568854#5 51568854#6 51568864#0 51568864#1 507094807 207799106 977668123 -954238846 -51568868#1 -51568868#0 -210873490 -210873500 -51219846 -4729140#2 -4729140#1 -4729140#0 4729142#3 4729142#4 399060559 -65288472#8 -65288472#7 -65288472#6 -65288472#5 -65288472#4 -65288472#3 -65288472#2 -65288472#1 -65288472#0 -2988718#6 -2988718#5 -2988718#4 -2988718#3 -2988718#2 -2988718#1 -2988718#0 -981008714" id="route86" repeat="10"/>


    <route edges="207714800 68338600#0 68338600#1 70562437 -42675703#1 -42675703#0 -35792959#1 -35792959#0 -856164070#2 -856164070#1 -856164070#0 35792405 297097142 977031652 2988628#0 2988628#1 39999438" id="route87" repeat="10"/>


    <route edges="93121887 1051854288 1051854284 1051854283 4578543 4081670#0 4081670#1 4081670#2 4081670#3 4081670#4 4081670#5 4081670#6 4081670#7 4081670#8 978248319 791411579 39760565 39760578#0 39760578#1 39760578#2 39760578#3 292124785#0 292124785#1 292124785#2 4578546 1328396414 207799114 1328396412 119966262#0 119966262#1 119966264 26562200#0" id="route88" repeat="10"/>


    <route edges="148935676 143483316#0 143483316#1 148935652#2 148935652#3 148935652#4 4729142#2 4729140#0 4729140#1 4729140#2 51219846 210873500 210873490 51568868#0 51568868#1 117690170 981268034 977668122 117690162 103401621 -4600230#3 -4600230#2 -4600230#1 -4600230#0 -1114962547 -1213065192#2 -1213065192#1 -1213065192#0 -1068231852 -977031655#1 -977031655#0 -4079720#3 -4079720#2 -4079720#1 -4079720#0 -4082170#1" id="route89" repeat="10"/>


    <route edges="143742721#1 457397324#2 457397324#3 457397324#4 210856077#0 210856077#1 -856164070#2 -856164070#1 -856164070#0 35792405 297097142 977031652 33778751 980633550#0 2988625 99858785 148935659#1 148935672 39760580 39760588 2988675#3 148935652#0 148935652#1 148935652#2 148935652#3 148935652#4 4729142#2 4729142#3 4729142#4 399060559 -65288472#8 -65288472#7 -65288472#6 -65288472#5 -65288472#4 -65288472#3 -65288472#2 -65288472#1 -65288472#0 -2988718#6 -2988718#5 28601535#0" id="route90" repeat="10"/>


    <route edges="148935652#2 148935652#3 148935652#4 4729142#2 4729140#0 4729140#1 4729140#2 51219846 210873500 210873490 51568868#0 51568868#1 117690170 981268034 977668122 117690162 103401621 -4600230#3 -4600230#2 -4600230#1 -4600230#0 -1114962547 -1213065192#2 -1213065192#1 -1213065192#0 -1068231852 -977031655#1 -977031655#0 -4079720#3 -4079720#2 -4079720#1 -4079720#0 -4082170#1 -4082170#0 -1039060565#1 -1039060565#0 -65757654#2 -65757654#1 -65757654#0 -64489933#9 -64489933#8 -64489933#7 -64489933#6 -64489933#5 -64489933#4 -64489933#3 -64489933#2 -64489933#1 -64489933#0 -515712517 -515712516" id="route91" repeat="10"/>


    <route edges="28746112 28746121 210873490 51568868#0 51568868#1 954238846 -977668123 -207799106 -507094807 -51568864#1 -51568864#0 -51568854#6 -51568854#5 -51568854#4 -51568854#3 -51568854#2 -51568854#1 -51568854#0 -93121875#7 -93121875#6 -93121875#5 -93121875#4 -93121875#3 -93121875#2 -93121875#1 -93121875#0 4578542 1051854283 4578543 4081670#0 4081670#1 4081670#2 4081670#3 4081670#4 4081670#5 4081670#6 4081670#7 4081670#8 978248319 791411579 39760565 39760578#0 39760578#1 39760578#2 39760578#3 292124785#0 292124785#1 292124785#2 4578546 1328396414 207799114 1328396412 119966262#0 119966262#1 119966264 208585619#0 208585619#1 922740525 1328396408 1328396409 25383761 1328396403 922740527 922740528" id="route92" repeat="10"/>


    <route edges="148895693#2 148895693#3 148895693#4 457397324#4 210856077#0 210856077#1 -856164070#2 -856164070#1 -856164070#0 35792405 297097142 977031652 33778751 980633550#0 2988625 99858785 148935659#1 148935672 39760580 39760588 2988675#3 148935652#0 148935652#1 148935652#2 148935652#3 148935652#4 4729142#2 4729140#0 4729140#1 4729140#2 51219846 210873500 210873490 51568868#0 51568868#1 954238846 -977668123 -207799106 207799106 977668123 -51568862 -28746537#0" id="route93" repeat="10"/>


    <route edges="-4082170#1 -4082170#0 -1039060565#1 -1039060565#0 -65757654#2 -65757654#1 -65757654#0 -64489933#9 -64489933#8 -64489933#7 -64489933#6 -64489933#5 -64489933#4 -64489933#3 -64489933#2 -64489933#1 -64489933#0 -515712517 4079712 65053911#0 65053911#1 65053911#2 39760563 63951486#0 63951486#1 981008714 2988718#0 2988718#1 2988718#2 2988718#3 2988718#4 2988718#5 2988718#6 65288472#0 65288472#1 65288472#2 65288472#3 65288472#4 65288472#5 65288472#6 65288472#7 65288472#8 399060558#0 399060558#1 4729142#0 4729142#1 4729142#2 4729140#0 4729140#1 4729140#2 51219846 210873500 210873490 51568868#0 51568868#1 117690170 117690166 -51568834#1 -51568834#0 -148935670" id="route94" repeat="10"/>


    <route edges="64489933#3 64489933#4 64489933#5 64489933#6 64489933#7 64489933#8 64489933#9 65757654#0 65757654#1 65757654#2 1039060565#0 1039060565#1 4082170#0 4082170#1 4079723#0 4079723#1 4079723#2 4079723#3 1169725323 1169725322#0 1169725322#1 210873489#0 210873489#1 148935669#0 148935669#1 71617435#0 71617435#1 71617435#2 71617435#3 71617435#4 -977031651#3 -977031651#2 -977031651#1 -977031651#0 -708952496 39999438 980633550#0 980633550#1 33778752 1169725324 977031656#0 977031656#1 977031656#2 33778748 977031653#0 977031653#1 33778749 977031657 977031652 2988628#0 35792141 143749335#0 143749335#1 143749335#2 143749336 856164070#0 856164070#1 856164070#2 35792959#0 35792959#1 42675703#0" id="route95" repeat="10"/>


    <route edges="25383759 922740528 1328396405 1328396406 922740526 -208585619#1 -208585619#0 -119966264 4812573 1328396410 4578545 -292124785#2 -292124785#1 -292124785#0 -39760578#3 -39760578#2 -39760578#1 -39760578#0 -39760565 -791411579 -978248319 -4081670#8 -4081670#7 -4081670#6 -4081670#5 -4081670#4 -4081670#3 -4081670#2 -4081670#1 -4081670#0 4578544 1051315787#0 1051315787#1 1051315787#2 93121891 -143742719#3 -143742719#2 -143742719#1 -143742719#0 -103401623#2 -103401623#1 -103401623#0 -103401622#7 -103401622#6 -103401622#5 -103401622#4 -103401622#3 -126548346#1 -126548346#0 28746347#0" id="route96" repeat="10"/>


    <!-- Method 1: Use vehicles with repeat attribute -->


    <vehicle depart="0.00" departLane="random" departSpeed="random" id="veh00" route="route0" type="veh_passenger">


        <param key="has.rerouting.device" value="false"/>


    </vehicle>


    <vehicle depart="18.00" departLane="random" departSpeed="random" id="veh1" route="route1" type="veh_passenger">


        <param key="has.rerouting.device" value="false"/>


    </vehicle>


    <vehicle depart="37.00" departLane="random" departSpeed="random" id="veh2" route="route2" type="veh_passenger">


        <param key="has.rerouting.device" value="false"/>


    </vehicle>


    <vehicle depart="56.00" departLane="random" departSpeed="random" id="veh3" route="route3" type="veh_passenger">


        <param key="has.rerouting.device" value="false"/>


    </vehicle>


    <vehicle depart="75.00" departLane="random" departSpeed="random" id="veh4" route="route4" type="veh_passenger">


        <param key="has.rerouting.device" value="false"/>


    </vehicle>


    <vehicle depart="93.00" departLane="random" departSpeed="random" id="veh5" route="route5" type="veh_passenger">


        <param key="has.rerouting.device" value="false"/>


    </vehicle>


    <vehicle depart="112.00" departLane="random" departSpeed="random" id="veh6" route="route6" type="veh_passenger">


        <param key="has.rerouting.device" value="false"/>


    </vehicle>


    <vehicle depart="131.00" departLane="random" departSpeed="random" id="veh7" route="route7" type="veh_passenger">


        <param key="has.rerouting.device" value="false"/>


    </vehicle>


    <vehicle depart="150.00" departLane="random" departSpeed="random" id="veh8" route="route8" type="veh_passenger">


        <param key="has.rerouting.device" value="false"/>


    </vehicle>


    <vehicle depart="168.00" departLane="random" departSpeed="random" id="veh9" route="route9" type="veh_passenger">


        <param key="has.rerouting.device" value="false"/>


    </vehicle>


    <vehicle depart="187.00" departLane="random" departSpeed="random" id="veh10" route="route10" type="veh_passenger">


        <param key="has.rerouting.device" value="false"/>


    </vehicle>


    <vehicle depart="206.00" departLane="random" departSpeed="random" id="veh11" route="route11" type="veh_passenger">


        <param key="has.rerouting.device" value="false"/>


    </vehicle>


    <vehicle depart="225.00" departLane="random" departSpeed="random" id="veh12" route="route12" type="veh_passenger">


        <param key="has.rerouting.device" value="false"/>


    </vehicle>


    <vehicle depart="243.00" departLane="random" departSpeed="random" id="veh14" route="route2" type="veh_passenger">


        <param key="has.rerouting.device" value="false"/>


    </vehicle>


    <vehicle depart="262.00" departLane="random" departSpeed="random" id="veh15" route="route14" type="veh_passenger">


        <param key="has.rerouting.device" value="false"/>


    </vehicle>


    <vehicle depart="281.00" departLane="random" departSpeed="random" id="veh16" route="route15" type="veh_passenger">


        <param key="has.rerouting.device" value="false"/>


    </vehicle>


    <vehicle depart="300.00" departLane="random" departSpeed="random" id="veh17" route="route16" type="veh_passenger">


        <param key="has.rerouting.device" value="false"/>


    </vehicle>


    <vehicle depart="318.00" departLane="random" departSpeed="random" id="veh18" route="route17" type="veh_passenger">


        <param key="has.rerouting.device" value="false"/>


    </vehicle>


    <vehicle depart="337.00" departLane="random" departSpeed="random" id="veh19" route="route18" type="veh_passenger">


        <param key="has.rerouting.device" value="false"/>


    </vehicle>


    <vehicle depart="356.00" departLane="random" departSpeed="random" id="veh20" route="route19" type="veh_passenger">


        <param key="has.rerouting.device" value="false"/>


    </vehicle>


    <vehicle depart="375.00" departLane="random" departSpeed="random" id="veh21" route="route20" type="veh_passenger">


        <param key="has.rerouting.device" value="false"/>


    </vehicle>


    <vehicle depart="393.00" departLane="random" departSpeed="random" id="veh22" route="route21" type="veh_passenger">


        <param key="has.rerouting.device" value="false"/>


    </vehicle>


    <vehicle depart="412.00" departLane="random" departSpeed="random" id="veh23" route="route22" type="veh_passenger">


        <param key="has.rerouting.device" value="false"/>


    </vehicle>


    <vehicle depart="431.00" departLane="random" departSpeed="random" id="veh24" route="route23" type="veh_passenger">


        <param key="has.rerouting.device" value="false"/>


    </vehicle>


    <vehicle depart="450.00" departLane="random" departSpeed="random" id="veh25" route="route24" type="veh_passenger">


        <param key="has.rerouting.device" value="false"/>


    </vehicle>


    <vehicle depart="468.00" departLane="random" departSpeed="random" id="veh26" route="route25" type="veh_passenger">


        <param key="has.rerouting.device" value="false"/>


    </vehicle>


    <vehicle depart="487.00" departLane="random" departSpeed="random" id="veh27" route="route26" type="veh_passenger">


        <param key="has.rerouting.device" value="false"/>


    </vehicle>


    <vehicle depart="506.00" departLane="random" departSpeed="random" id="veh28" route="route27" type="veh_passenger">


        <param key="has.rerouting.device" value="false"/>


    </vehicle>


    <vehicle depart="525.00" departLane="random" departSpeed="random" id="veh29" route="route28" type="veh_passenger">


        <param key="has.rerouting.device" value="false"/>


    </vehicle>


    <vehicle depart="543.00" departLane="random" departSpeed="random" id="veh30" route="route29" type="veh_passenger">


        <param key="has.rerouting.device" value="false"/>


    </vehicle>


    <vehicle depart="562.00" departLane="random" departSpeed="random" id="veh31" route="route30" type="veh_passenger">


        <param key="has.rerouting.device" value="false"/>


    </vehicle>


    <vehicle depart="581.00" departLane="random" departSpeed="random" id="veh32" route="route31" type="veh_passenger">


        <param key="has.rerouting.device" value="false"/>


    </vehicle>


    <vehicle depart="600.00" departLane="random" departSpeed="random" id="veh33" route="route32" type="veh_passenger">


        <param key="has.rerouting.device" value="false"/>


    </vehicle>


    <vehicle depart="618.00" departLane="random" departSpeed="random" id="veh34" route="route33" type="veh_passenger">


        <param key="has.rerouting.device" value="false"/>


    </vehicle>


    <vehicle depart="637.00" departLane="random" departSpeed="random" id="veh35" route="route34" type="veh_passenger">


        <param key="has.rerouting.device" value="false"/>


    </vehicle>


    <vehicle depart="656.00" departLane="random" departSpeed="random" id="veh36" route="route35" type="veh_passenger">


        <param key="has.rerouting.device" value="false"/>


    </vehicle>


    <vehicle depart="675.00" departLane="random" departSpeed="random" id="veh37" route="route36" type="veh_passenger">


        <param key="has.rerouting.device" value="false"/>


    </vehicle>


    <vehicle depart="693.00" departLane="random" departSpeed="random" id="veh38" route="route37" type="veh_passenger">


        <param key="has.rerouting.device" value="false"/>


    </vehicle>


    <vehicle depart="712.00" departLane="random" departSpeed="random" id="veh39" route="route38" type="veh_passenger">


        <param key="has.rerouting.device" value="false"/>


    </vehicle>


    <vehicle depart="731.00" departLane="random" departSpeed="random" id="veh40" route="route39" type="veh_passenger">


        <param key="has.rerouting.device" value="false"/>


    </vehicle>


    <vehicle depart="750.00" departLane="random" departSpeed="random" id="veh41" route="route40" type="veh_passenger">


        <param key="has.rerouting.device" value="false"/>


    </vehicle>


    <vehicle depart="768.00" departLane="random" departSpeed="random" id="veh42" route="route41" type="veh_passenger">


        <param key="has.rerouting.device" value="false"/>


    </vehicle>


    <vehicle depart="787.00" departLane="random" departSpeed="random" id="veh43" route="route42" type="veh_passenger">


        <param key="has.rerouting.device" value="false"/>


    </vehicle>


    <vehicle depart="806.00" departLane="random" departSpeed="random" id="veh44" route="route43" type="veh_passenger">


        <param key="has.rerouting.device" value="false"/>


    </vehicle>


    <vehicle depart="825.00" departLane="random" departSpeed="random" id="veh45" route="route44" type="veh_passenger">


        <param key="has.rerouting.device" value="false"/>


    </vehicle>


    <vehicle depart="843.00" departLane="random" departSpeed="random" id="veh46" route="route45" type="veh_passenger">


        <param key="has.rerouting.device" value="false"/>


    </vehicle>


    <vehicle depart="862.00" departLane="random" departSpeed="random" id="veh47" route="route46" type="veh_passenger">


        <param key="has.rerouting.device" value="false"/>


    </vehicle>


    <vehicle depart="881.00" departLane="random" departSpeed="random" id="veh48" route="route47" type="veh_passenger">


        <param key="has.rerouting.device" value="false"/>


    </vehicle>


    <vehicle depart="900.00" departLane="random" departSpeed="random" id="veh49" route="route48" type="veh_passenger">


        <param key="has.rerouting.device" value="false"/>


    </vehicle>


    <vehicle depart="918.00" departLane="random" departSpeed="random" id="veh50" route="route49" type="veh_passenger">


        <param key="has.rerouting.device" value="false"/>


    </vehicle>


    <vehicle depart="937.00" departLane="random" departSpeed="random" id="veh51" route="route50" type="veh_passenger">


        <param key="has.rerouting.device" value="false"/>


    </vehicle>


    <vehicle depart="956.00" departLane="random" departSpeed="random" id="veh52" route="route51" type="veh_passenger">


        <param key="has.rerouting.device" value="false"/>


    </vehicle>


    <vehicle depart="975.00" departLane="random" departSpeed="random" id="veh53" route="route52" type="veh_passenger">


        <param key="has.rerouting.device" value="false"/>


    </vehicle>


    <vehicle depart="993.00" departLane="random" departSpeed="random" id="veh54" route="route53" type="veh_passenger">


        <param key="has.rerouting.device" value="false"/>


    </vehicle>


    <vehicle depart="1012.00" departLane="random" departSpeed="random" id="veh55" route="route54" type="veh_passenger">


        <param key="has.rerouting.device" value="false"/>


    </vehicle>


    <vehicle depart="1031.00" departLane="random" departSpeed="random" id="veh56" route="route55" type="veh_passenger">


        <param key="has.rerouting.device" value="false"/>


    </vehicle>


    <vehicle depart="1050.00" departLane="random" departSpeed="random" id="veh57" route="route56" type="veh_passenger">


        <param key="has.rerouting.device" value="false"/>


    </vehicle>


    <vehicle depart="1068.00" departLane="random" departSpeed="random" id="veh58" route="route57" type="veh_passenger">


        <param key="has.rerouting.device" value="false"/>


    </vehicle>


    <vehicle depart="1087.00" departLane="random" departSpeed="random" id="veh59" route="route58" type="veh_passenger">


        <param key="has.rerouting.device" value="false"/>


    </vehicle>


    <vehicle depart="1106.00" departLane="random" departSpeed="random" id="veh60" route="route59" type="veh_passenger">


        <param key="has.rerouting.device" value="false"/>


    </vehicle>


    <vehicle depart="1125.00" departLane="random" departSpeed="random" id="veh61" route="route60" type="veh_passenger">


        <param key="has.rerouting.device" value="false"/>


    </vehicle>


    <vehicle depart="1143.00" departLane="random" departSpeed="random" id="veh62" route="route61" type="veh_passenger">


        <param key="has.rerouting.device" value="false"/>


    </vehicle>


    <vehicle depart="1162.00" departLane="random" departSpeed="random" id="veh63" route="route62" type="veh_passenger">


        <param key="has.rerouting.device" value="false"/>


    </vehicle>


    <vehicle depart="1181.00" departLane="random" departSpeed="random" id="veh65" route="route63" type="veh_passenger">


        <param key="has.rerouting.device" value="false"/>


    </vehicle>


    <vehicle depart="1200.00" departLane="random" departSpeed="random" id="veh66" route="route6" type="veh_passenger">


        <param key="has.rerouting.device" value="false"/>


    </vehicle>


    <vehicle depart="1218.00" departLane="random" departSpeed="random" id="veh67" route="route65" type="veh_passenger">


        <param key="has.rerouting.device" value="false"/>


    </vehicle>


    <vehicle depart="1237.00" departLane="random" departSpeed="random" id="veh68" route="route66" type="veh_passenger">


        <param key="has.rerouting.device" value="false"/>


    </vehicle>


    <vehicle depart="1256.00" departLane="random" departSpeed="random" id="veh69" route="route67" type="veh_passenger">


        <param key="has.rerouting.device" value="false"/>


    </vehicle>


    <vehicle depart="1275.00" departLane="random" departSpeed="random" id="veh70" route="route68" type="veh_passenger">


        <param key="has.rerouting.device" value="false"/>


    </vehicle>


    <vehicle depart="1293.00" departLane="random" departSpeed="random" id="veh71" route="route69" type="veh_passenger">


        <param key="has.rerouting.device" value="false"/>


    </vehicle>


    <vehicle depart="1312.00" departLane="random" departSpeed="random" id="veh72" route="route70" type="veh_passenger">


        <param key="has.rerouting.device" value="false"/>


    </vehicle>


    <vehicle depart="1331.00" departLane="random" departSpeed="random" id="veh73" route="route71" type="veh_passenger">


        <param key="has.rerouting.device" value="false"/>


    </vehicle>


    <vehicle depart="1350.00" departLane="random" departSpeed="random" id="veh74" route="route72" type="veh_passenger">


        <param key="has.rerouting.device" value="false"/>


    </vehicle>


    <vehicle depart="1368.00" departLane="random" departSpeed="random" id="veh75" route="route73" type="veh_passenger">


        <param key="has.rerouting.device" value="false"/>


    </vehicle>


    <vehicle depart="1387.00" departLane="random" departSpeed="random" id="veh76" route="route74" type="veh_passenger">


        <param key="has.rerouting.device" value="false"/>


    </vehicle>


    <vehicle depart="1406.00" departLane="random" departSpeed="random" id="veh77" route="route75" type="veh_passenger">


        <param key="has.rerouting.device" value="false"/>


    </vehicle>


    <vehicle depart="1425.00" departLane="random" departSpeed="random" id="veh78" route="route76" type="veh_passenger">


        <param key="has.rerouting.device" value="false"/>


    </vehicle>


    <vehicle depart="1443.00" departLane="random" departSpeed="random" id="veh80" route="route77" type="veh_passenger">


        <param key="has.rerouting.device" value="false"/>


    </vehicle>


    <vehicle depart="1462.00" departLane="random" departSpeed="random" id="veh81" route="route78" type="veh_passenger">


        <param key="has.rerouting.device" value="false"/>


    </vehicle>


    <vehicle depart="1481.00" departLane="random" departSpeed="random" id="veh82" route="route9" type="veh_passenger">


        <param key="has.rerouting.device" value="false"/>


    </vehicle>


    <vehicle depart="1500.00" departLane="random" departSpeed="random" id="veh84" route="route80" type="veh_passenger">


        <param key="has.rerouting.device" value="false"/>


    </vehicle>


    <vehicle depart="1518.00" departLane="random" departSpeed="random" id="veh85" route="route81" type="veh_passenger">


        <param key="has.rerouting.device" value="false"/>


    </vehicle>


    <vehicle depart="1537.00" departLane="random" departSpeed="random" id="veh86" route="route82" type="veh_passenger">


        <param key="has.rerouting.device" value="false"/>


    </vehicle>


    <vehicle depart="1556.00" departLane="random" departSpeed="random" id="veh87" route="route19" type="veh_passenger">


        <param key="has.rerouting.device" value="false"/>


    </vehicle>


    <vehicle depart="1575.00" departLane="random" departSpeed="random" id="veh88" route="route84" type="veh_passenger">


        <param key="has.rerouting.device" value="false"/>


    </vehicle>


    <vehicle depart="1593.00" departLane="random" departSpeed="random" id="veh89" route="route85" type="veh_passenger">


        <param key="has.rerouting.device" value="false"/>


    </vehicle>


    <vehicle depart="1612.00" departLane="random" departSpeed="random" id="veh90" route="route86" type="veh_passenger">


        <param key="has.rerouting.device" value="false"/>


    </vehicle>


    <vehicle depart="1631.00" departLane="random" departSpeed="random" id="veh91" route="route87" type="veh_passenger">


        <param key="has.rerouting.device" value="false"/>


    </vehicle>


    <vehicle depart="1650.00" departLane="random" departSpeed="random" id="veh92" route="route88" type="veh_passenger">


        <param key="has.rerouting.device" value="false"/>


    </vehicle>


    <vehicle depart="1668.00" departLane="random" departSpeed="random" id="veh93" route="route89" type="veh_passenger">


        <param key="has.rerouting.device" value="false"/>


    </vehicle>


    <vehicle depart="1687.00" departLane="random" departSpeed="random" id="veh94" route="route90" type="veh_passenger">


        <param key="has.rerouting.device" value="false"/>


    </vehicle>


    <vehicle depart="1706.00" departLane="random" departSpeed="random" id="veh95" route="route91" type="veh_passenger">


        <param key="has.rerouting.device" value="false"/>


    </vehicle>


    <vehicle depart="1725.00" departLane="random" departSpeed="random" id="veh96" route="route92" type="veh_passenger">


        <param key="has.rerouting.device" value="false"/>


    </vehicle>


    <vehicle depart="1743.00" departLane="random" departSpeed="random" id="veh97" route="route93" type="veh_passenger">


        <param key="has.rerouting.device" value="false"/>


    </vehicle>


    <vehicle depart="1762.00" departLane="random" departSpeed="random" id="veh98" route="route94" type="veh_passenger">


        <param key="has.rerouting.device" value="false"/>


    </vehicle>


    <vehicle depart="1781.00" departLane="random" departSpeed="random" id="veh99" route="route95" type="veh_passenger">


        <param key="has.rerouting.device" value="false"/>


    </vehicle>


    <vehicle depart="1800.00" departLane="random" departSpeed="random" id="veh100" route="route96" type="veh_passenger">


        <param key="has.rerouting.device" value="false"/>


    </vehicle>


</routes>
